ffmpeg/__init__.py
ffmpeg/errors.py
ffmpeg/ffmpeg.py
ffmpeg/file.py
ffmpeg/options.py
ffmpeg/progress.py
ffmpeg/protocol.py
ffmpeg/statistics.py
ffmpeg/types.py
ffmpeg/utils.py
ffmpeg/asyncio/__init__.py
ffmpeg/asyncio/ffmpeg.py
ffmpeg/asyncio/utils.py
python_ffmpeg-2.0.12.dist-info/LICENSE
python_ffmpeg-2.0.12.dist-info/METADATA
python_ffmpeg-2.0.12.dist-info/WHEEL
python_ffmpeg-2.0.12.dist-info/top_level.txt
python_ffmpeg-2.0.12.dist-info/RECORD
