Metadata-Version: 2.1
Name: python-ffmpeg
Version: 2.0.12
Summary: A python binding for FFmpeg which provides sync and async APIs
Home-page: https://github.com/jonghwanhyeon/python-ffmpeg
Author: Jonghwan Hyeon
Author-email: jonghwanhyeon93@gmail.com
License: MIT
Keywords: ffmpeg,asyncio
Classifier: Development Status :: 4 - Beta
Classifier: Intended Audience :: Developers
Classifier: License :: OSI Approved :: MIT License
Classifier: Programming Language :: Python :: 3
Classifier: Programming Language :: Python :: 3 :: Only
Requires-Python: >=3.7
License-File: LICENSE
Requires-Dist: pyee
Requires-Dist: typing_extensions
